modelutils/__init__.py
modelutils/utils.py
nntestdbx/__init__.py
nntestdbx/sentence_model.py
nntestdbx-0.11.dist-info/METADATA
nntestdbx-0.11.dist-info/WHEEL
nntestdbx-0.11.dist-info/top_level.txt
nntestdbx-0.11.dist-info/RECORD
