Metadata-Version: 2.1
Name: nntestdbx
Version: 0.11
Summary: demo wheel
Home-page: UNKNOWN
License: UNKNOWN
Platform: UNKNOWN
